goodplay/__init__.py
goodplay/cli.py
goodplay/context.py
goodplay/goodplaytester.py
goodplay/junitxml.py
goodplay/plugin.py
goodplay/ansible_support/__init__.py
goodplay/ansible_support/inventory.py
goodplay/ansible_support/playbook.py
goodplay/ansible_support/runner.py
goodplay/ansible_support/callback_plugin/goodplay.py
goodplay/ansible_support/connection_plugin/goodplaydocker.py
goodplay/docker_support/__init__.py
goodplay/utils/__init__.py
goodplay/utils/subprocess.py
goodplay-0.12.0.dist-info/AUTHORS.rst
goodplay-0.12.0.dist-info/LICENSE
goodplay-0.12.0.dist-info/METADATA
goodplay-0.12.0.dist-info/WHEEL
goodplay-0.12.0.dist-info/entry_points.txt
goodplay-0.12.0.dist-info/top_level.txt
goodplay-0.12.0.dist-info/RECORD
