Metadata-Version: 2.1
Name: goodplay
Version: 0.12.0
Summary: goodplay enables you to test your deployments and distributed software infrastructure by reusing your existing knowledge of Ansible.
Home-page: https://goodplay.io/
Author: Benjamin Schwarze
Author-email: benjamin.schwarze@mailboxd.de
Maintainer: Benjamin Schwarze
Maintainer-email: benjamin.schwarze@mailboxd.de
License: Apache License 2.0
Keywords: goodplay,good,play,test,deployment,ansible,playbook,role,integration,system,tdd,configuration,management
Platform: UNKNOWN
Classifier: Development Status :: 4 - Beta
Classifier: Environment :: Plugins
Classifier: Framework :: Pytest
Classifier: Intended Audience :: Developers
Classifier: License :: OSI Approved :: Apache Software License
Classifier: Operating System :: MacOS :: MacOS X
Classifier: Operating System :: POSIX :: Linux
Classifier: Programming Language :: Python
Classifier: Programming Language :: Python :: 2.7
Classifier: Programming Language :: Python :: 3.6
Classifier: Programming Language :: Python :: 3.7
Classifier: Topic :: Software Development :: Quality Assurance
Classifier: Topic :: Software Development :: Testing
Requires-Dist: ansible (>=2.5)
Requires-Dist: cached-property (>=1.3.1)
Requires-Dist: docker-compose (>=1.22.0)
Requires-Dist: py (>=1.4.34)
Requires-Dist: pytest (>=3.5.0)
Requires-Dist: sarge (>=0.1.5)
